edentity/__init__.py
edentity/__main__.py
edentity/_version.py
edentity/utils/__init__.py
edentity/utils/configs.py
edentity/utils/snakemake_args.py
edentity/workflow/Dockerfile
edentity/workflow/Snakefile
edentity/workflow/rules/chimera.smk
edentity/workflow/rules/denoise.smk
edentity/workflow/rules/dereplication.smk
edentity/workflow/rules/filter.smk
edentity/workflow/rules/merge.smk
edentity/workflow/rules/search_exact.smk
edentity/workflow/rules/trimming.smk
edentity/workflow/scripts/chimera.py
edentity/workflow/scripts/create_multiqc_filelist.py
edentity/workflow/scripts/custom_multiqc_module.py
edentity/workflow/scripts/denoise.py
edentity/workflow/scripts/dereplication.py
edentity/workflow/scripts/esv_table.py
edentity/workflow/scripts/filter.py
edentity/workflow/scripts/merge.py
edentity/workflow/scripts/primerHandler.py
edentity/workflow/scripts/runtime.py
edentity/workflow/scripts/search_exact.py
edentity/workflow/scripts/trimming.py
edentity-1.5.4.dist-info/licenses/LICENSE
edentity-1.5.4.dist-info/METADATA
edentity-1.5.4.dist-info/WHEEL
edentity-1.5.4.dist-info/entry_points.txt
edentity-1.5.4.dist-info/top_level.txt
edentity-1.5.4.dist-info/RECORD
