Metadata-Version: 2.4
Name: edentity
Version: 1.5.4
Summary: A Snakemake-based pipeline for amplicon processing
Author-email: Luka Lenaroto <luka.lenaroto@naturalis.nl>, Pierre-Etienne Cholley <pierreetienne.cholley@naturalis.nl>, Dick Groenenberg <dick.groenenberg@naturalis.nl>, Edwin den Haas <edwin.denhaas@naturalis.nl>, Dominika Kresa <dominika.kresa@naturalis.nl>, Rutger Vos <rutger.vos@naturalis.nl>
License:                                  Apache License
Classifier: Programming Language :: Python :: 3
Classifier: Operating System :: OS Independent
Classifier: License :: OSI Approved :: Apache Software License
Requires-Python: >=3.10
License-File: LICENSE
Requires-Dist: snakemake>=8.16.0
Requires-Dist: polars>=1.30.0
Requires-Dist: pyarrow
Requires-Dist: nbitk>=0.5.9
Dynamic: license-file
